pwspy/__init__.py
pwspy/version.py
pwspy/analysis/__init__.py
pwspy/analysis/_abstract.py
pwspy/analysis/dynamics.py
pwspy/analysis/pws.py
pwspy/analysis/warnings.py
pwspy/analysis/_resources/defaultAnalysisSettings/Legacy_analysis.json
pwspy/analysis/_resources/defaultAnalysisSettings/Recommended_analysis.json
pwspy/analysis/compilation/__init__.py
pwspy/analysis/compilation/_abstract.py
pwspy/analysis/compilation/_dynamics.py
pwspy/analysis/compilation/_generic.py
pwspy/analysis/compilation/_pws.py
pwspy/analysis/examples/__init__.py
pwspy/analysis/examples/dynamics/__init__.py
pwspy/analysis/examples/dynamics/_matlabTranslations/RMS_T_General.py
pwspy/analysis/examples/dynamics/_matlabTranslations/__init__.py
pwspy/analysis/examples/dynamics/_matlabTranslations/autoCorr2019.py
pwspy/analysis/examples/dynamics/_matlabTranslations/compileDynamics.py
pwspy/analysis/examples/dynamics/_matlabTranslations/timeseries2imagecube_general.py
pwspy/dataTypes/__init__.py
pwspy/dataTypes/_data.py
pwspy/dataTypes/_metadata.py
pwspy/dataTypes/_other.py
pwspy/dataTypes/jsonSchemas/DynMetaData.json
pwspy/dataTypes/jsonSchemas/ICMetaData.json
pwspy/dataTypes/jsonSchemas/MetaDataBase.json
pwspy/examples/ROItoMirror.py
pwspy/examples/__init__.py
pwspy/examples/flatFieldVisualizer.py
pwspy/examples/limitedOPDSigma.py
pwspy/examples/plotITOThinFilmCalibration.py
pwspy/examples/pwsAnalysis.py
pwspy/examples/syntheticMirror.py
pwspy/examples/findOPDSurface/__init__.py
pwspy/examples/findOPDSurface/activeContour/__init__.py
pwspy/examples/findOPDSurface/activeContour/activeContour.py
pwspy/examples/findOPDSurface/activeContour/funcs.py
pwspy/examples/findOPDSurface/peakDetection/__init__.py
pwspy/examples/findOPDSurface/peakDetection/findOPDSurface.py
pwspy/examples/findOPDSurface/peakDetection/funcs.py
pwspy/utility/_GoogleDriveDownloader.py
pwspy/utility/__init__.py
pwspy/utility/fileIO.py
pwspy/utility/fluorescence.py
pwspy/utility/machineVision.py
pwspy/utility/misc.py
pwspy-0.2.dist-info/COPYING
pwspy-0.2.dist-info/METADATA
pwspy-0.2.dist-info/WHEEL
pwspy-0.2.dist-info/top_level.txt
pwspy-0.2.dist-info/RECORD
